ws_conan_scanner/__init__.py
ws_conan_scanner/_version.py
ws_conan_scanner/conan_scanner.py
ws_conan_scanner/utils.py
ws_conan_scanner-22.8.4.1.dist-info/LICENSE
ws_conan_scanner-22.8.4.1.dist-info/METADATA
ws_conan_scanner-22.8.4.1.dist-info/WHEEL
ws_conan_scanner-22.8.4.1.dist-info/entry_points.txt
ws_conan_scanner-22.8.4.1.dist-info/top_level.txt
ws_conan_scanner-22.8.4.1.dist-info/RECORD
