Metadata-Version: 2.1
Name: ws-conan-scanner
Version: 22.8.4.1
Summary: WS Conan Scanner
Home-page: https://github.com/whitesource-ps/ws-conan-scanner
Author: WhiteSource Professional Services
Author-email: ps@whitesourcesoftware.com
License: LICENSE.txt
Platform: UNKNOWN
Classifier: Programming Language :: Python :: 3.7
Classifier: Programming Language :: Python :: 3.8
Classifier: Programming Language :: Python :: 3.9
Classifier: License :: OSI Approved :: Apache Software License
Classifier: Operating System :: OS Independent
Requires-Python: >=3.7
License-File: LICENSE
Requires-Dist: setuptools (~=57.0.0)
Requires-Dist: requests (~=2.27.0)
Requires-Dist: configparser (~=5.0.2)
Requires-Dist: DateTime (~=4.3)
Requires-Dist: PyYAML (~=5.4.1)
Requires-Dist: ws-sdk (==22.8.4.1)
Requires-Dist: urllib3 (~=1.26.7)
